LICENSE.txt
README.rst
setup.py
bin/wireguard
tests/test_config.py
tests/test_config_attributes.py
tests/test_customizations.py
tests/test_json.py
tests/test_peer_sets.py
tests/test_peers.py
tests/test_qrcode.py
tests/test_server.py
tests/test_utils.py
wireguard/__init__.py
wireguard/base.py
wireguard/config.py
wireguard/constants.py
wireguard/peer.py
wireguard/server.py
wireguard/service.py
wireguard.egg-info/PKG-INFO
wireguard.egg-info/SOURCES.txt
wireguard.egg-info/dependency_links.txt
wireguard.egg-info/requires.txt
wireguard.egg-info/top_level.txt
wireguard/cli/__init__.py
wireguard/cli/config.py
wireguard/cli/service.py
wireguard/utils/__init__.py
wireguard/utils/config.py
wireguard/utils/json.py
wireguard/utils/keys.py
wireguard/utils/sets.py
wireguard/utils/subnets.py