Metadata-Version: 2.4
Name: wireguard
Version: 1.0.2
Summary: Wireguard Utilities
Home-page: https://github.com/fictive-kin/wireguard
Author: Fictive Kin LLC
Author-email: hello@fictivekin.com
Maintainer: Fictive Kin LLC
Maintainer-email: hello@fictivekin.com
License: MIT
Classifier: Development Status :: 4 - Beta
Classifier: Programming Language :: Python :: 3.6
Classifier: Programming Language :: Python :: 3.7
Classifier: Programming Language :: Python :: 3.8
Classifier: Programming Language :: Python :: 3.9
Classifier: Programming Language :: Python :: 3.10
Classifier: Programming Language :: Python :: 3.11
Classifier: Programming Language :: Python :: 3.12
Classifier: Programming Language :: Python :: 3.13
Classifier: Topic :: Software Development
Classifier: Topic :: System :: Networking
Classifier: Topic :: Utilities
Requires-Python: >=3.6
License-File: LICENSE.txt
Requires-Dist: click
Requires-Dist: pynacl
Requires-Dist: subnet-utils
Provides-Extra: qr
Requires-Dist: qrcode[pil]; extra == "qr"
Dynamic: author
Dynamic: author-email
Dynamic: classifier
Dynamic: description
Dynamic: home-page
Dynamic: license
Dynamic: license-file
Dynamic: maintainer
Dynamic: maintainer-email
Dynamic: provides-extra
Dynamic: requires-dist
Dynamic: requires-python
Dynamic: summary
